highlight_video_maker/__init__.py
highlight_video_maker/logger.py
highlight_video_maker/main.py
highlight_video_maker-0.2.3.dist-info/METADATA
highlight_video_maker-0.2.3.dist-info/WHEEL
highlight_video_maker-0.2.3.dist-info/entry_points.txt
highlight_video_maker-0.2.3.dist-info/licenses/LICENSE
highlight_video_maker-0.2.3.dist-info/RECORD
