Metadata-Version: 2.4
Name: highlight_video_maker
Version: 0.2.3
Summary: A utility to take several video inputs, take the loudest points, and create a compilation of them with smooth transitions
Project-URL: Homepage, https://github.com/MichaByte/highlight-video-maker
Project-URL: Issues, https://github.com/MichaByte/highlight-video-maker/issues
Author-email: Micha Albert <micha@2231.tech>
License-Expression: MIT
License-File: LICENSE
Classifier: Operating System :: POSIX :: Linux
Classifier: Programming Language :: Python :: 3
Requires-Python: >=3.12
Requires-Dist: click
